setup.py
distributions_function/Binomialdistribution.py
distributions_function/Gaussiandistribution.py
distributions_function/Generaldistribution.py
distributions_function/__init__.py
distributions_function.egg-info/PKG-INFO
distributions_function.egg-info/SOURCES.txt
distributions_function.egg-info/dependency_links.txt
distributions_function.egg-info/not-zip-safe
distributions_function.egg-info/top_level.txt